[
  {
    "pyre_fighter": "20 Cresting Magma",
    "pyre_comic_link": "https://cubari.moe/read/imgur/V1EHfBE/1/1/",
    "bastion_fighter": "48 Truth Alights",
    "bastion_comic_link": "https://cubari.moe/read/imgur/z4HvwSm/1/1/ "
  },
  {
    "pyre_fighter": "28 Quicksilver",
    "pyre_comic_link": "https://cubari.moe/read/gist/Z2lzdC94cmFib2hyb2svYTk2ZTlmYzM4YTQ1Njg2ZmYxYTE2NzlkY2NjZTE5MzYvcmF3Lw/",
    "bastion_fighter": "Aloysius & the Dragon",
    "bastion_comic_link": "https://imgur.com/a/GaqCgh5"
  },
  {
    "pyre_fighter": "Borginskov",
    "pyre_comic_link": "https://cubari.moe/read/gist/Z2lzdC94cmFib2hyb2svYTk2ZTlmYzM4YTQ1Njg2ZmYxYTE2NzlkY2NjZTE5MzYvcmF3Lw/",
    "bastion_fighter": "Am Sham Ka Bedlam",
    "bastion_comic_link": "https://cubari.moe/read/imgur/iwFpUyh/1/1/"
  },
  {
    "pyre_fighter": "Burial at Sea",
    "pyre_comic_link": "https://cubari.moe/read/imgur/uGfpSZw/1/1/",
    "bastion_fighter": "Disassembly",
    "bastion_comic_link": "https://cubari.moe/read/imgur/0Kq4cVu/1/1/"
  },
  {
    "pyre_fighter": "Eckobu",
    "pyre_comic_link": "https://imgur.com/a/eATOgun",
    "bastion_fighter": "Hok, JJ, Cupid",
    "bastion_comic_link": "https://imgur.com/a/S3EGJpG"
  },
  {
    "pyre_fighter": "Eckobu",
    "pyre_comic_link": "https://cubari.moe/read/imgur/b8qezRA/1/1/",
    "bastion_fighter": "Mary Bovente, Herb & P.No.K.O",
    "bastion_comic_link": "https://imgur.com/a/dFOpNQY"
  },
  {
    "pyre_fighter": "Erasmus & Heedless",
    "pyre_comic_link": "https://cubari.moe/read/imgur/ebnYZjU/1/1/",
    "bastion_fighter": "Oboe",
    "bastion_comic_link": "https://imgur.com/a/3Ms0eVn"
  },
  {
    "pyre_fighter": "Harmony Pissblood",
    "pyre_comic_link": "https://cubari.moe/read/imgur/pYcQnNJ/1/1/",
    "bastion_fighter": "Sia",
    "bastion_comic_link": "https://cubari.moe/read/imgur/Lg3Ax7B/1/1/"
  },
  {
    "pyre_fighter": "Jake Duerhaust",
    "pyre_comic_link": "https://imgur.com/a/2EQlaWw",
    "bastion_fighter": "Solis",
    "bastion_comic_link": "https://cubari.moe/read/imgur/iVvah4x/1/1/"
  },
  {
    "pyre_fighter": "Jude",
    "pyre_comic_link": "https://cubari.moe/read/imgur/pGSWcen/1/1/",
    "bastion_fighter": "Spaceman Dan",
    "bastion_comic_link": "https://imgur.com/gallery/8sCQ7cV"
  },
  {
    "pyre_fighter": "Kaiserjager",
    "pyre_comic_link": "(Collab with Bastion)",
    "bastion_fighter": "Virita",
    "bastion_comic_link": "https://imgur.com/gallery/Aj0zwCg"
  },
  {
    "pyre_fighter": "Kilroy",
    "pyre_comic_link": "https://cubari.moe/read/imgur/ebnYZjU/1/1/",
    "bastion_fighter": "Who Wanders",
    "bastion_comic_link": "https://imgur.com/a/XlmIp95"
  },
  {
    "pyre_fighter": "Mad Tooth D",
    "pyre_comic_link": "https://cubari.moe/read/imgur/b8qezRA/1/1/",
    "bastion_fighter": "",
    "bastion_comic_link": ""
  },
  {
    "pyre_fighter": "Pretzel Man",
    "pyre_comic_link": "https://cubari.moe/read/gist/Z2lzdC94cmFib2hyb2svYTk2ZTlmYzM4YTQ1Njg2ZmYxYTE2NzlkY2NjZTE5MzYvcmF3Lw/",
    "bastion_fighter": "",
    "bastion_comic_link": ""
  },
  {
    "pyre_fighter": "Rabbit Mage",
    "pyre_comic_link": "https://imgur.com/a/HCEa9Wo",
    "bastion_fighter": "",
    "bastion_comic_link": ""
  },
  {
    "pyre_fighter": "Randio",
    "pyre_comic_link": "https://imgur.com/a/GkTUsAQ",
    "bastion_fighter": "",
    "bastion_comic_link": ""
  },
  {
    "pyre_fighter": "Sylvia",
    "pyre_comic_link": "https://cubari.moe/read/imgur/b8qezRA/1/1/",
    "bastion_fighter": "",
    "bastion_comic_link": ""
  },
  {
    "pyre_fighter": "The Kings Players",
    "pyre_comic_link": "https://imgur.com/a/sCws5xz",
    "bastion_fighter": "",
    "bastion_comic_link": ""
  },
  {
    "pyre_fighter": "Vale",
    "pyre_comic_link": "https://cubari.moe/read/imgur/b8qezRA/1/1/",
    "bastion_fighter": "",
    "bastion_comic_link": ""
  },
  {
    "pyre_fighter": "Vesna",
    "pyre_comic_link": "https://cubari.moe/read/imgur/ebnYZjU/1/1/",
    "bastion_fighter": "",
    "bastion_comic_link": ""
  }
]
